[
    {
        "id":"old/index",
        "name":"主页",
        "link":"index.html",
        "is_direct":true
    },
    {
        "id":"old/list",
        "name":"整合包版本列表",
        "link":"list.html",
        "is_direct":true
    },
    {
        "id":"old/information",
        "name":"服务器信息",
        "link":"information.html",
        "is_direct":true
    },
    {
        "id":"old/update",
        "name":"更新日志",
        "link":"update.html",
        "is_direct":true
    },
    {
        "name":"前往新版官网",
        "link":"/",
        "is_direct":true
    },
    {
        "name":"更多",
        "is_direct":false,
        "children":[
            {
                "name":"网页地图",
                "link":"https://yr-map.qingu.moe/",
                "outlink":true
            },
            {
                "name":"服务器网页手册",
                "link":"https://docs.youran.qingu.moe/",
                "outlink":true
            },
            {
                "name":"MC百科找服玩",
                "link":"https://play.mcmod.cn/sv20185890.html",
                "outlink":true
            },
            {
                "name":"服务器规则",
                "link":"https://docs.qq.com/doc/DVHpzQUdQSlFuT0ha",
                "outlink":true
            },
            {
                "name":"HMCL启动器",
                "link":"https://hmcl.huangyuhui.net",
                "outlink":true
            },
            {
                "name":"Minecraft Java游玩指南",
                "link":"https://docs.qq.com/doc/DVGpxbW9xZ2JOR1dS",
                "outlink":true
            }
        ]
    },
    {
        "name":"官网镜像",
        "is_direct":false,
        "children":[
            {
                "name":"主要",
                "link":"https://youran.qingu.moe/",
                "outlink":true
            },
            {
                "name":"备用",
                "link":"https://mirror.youranserver.top/",
                "outlink":true
            }
        ]
    }
]